p2pshare/__init__.py
p2pshare/main.py
p2pshare/receiver.py
p2pshare/sender.py
p2pshare/utils.py
p2pshare_cli-0.1.1.dist-info/licenses/LICENSE
p2pshare_cli-0.1.1.dist-info/METADATA
p2pshare_cli-0.1.1.dist-info/WHEEL
p2pshare_cli-0.1.1.dist-info/top_level.txt
p2pshare_cli-0.1.1.dist-info/RECORD
