Metadata-Version: 2.4
Name: p2pshare-cli
Version: 0.1.1
Summary: A CLI tool for peer-to-peer file sharing with QR codes
Author-email: zhuosiwaaa <you@example.com>
License-File: LICENSE
Requires-Dist: waitress
Requires-Dist: qrcode
Requires-Dist: flask
Requires-Dist: setuptools
Requires-Dist: Werkzeug
Dynamic: license-file
